vkslaves/__init__.py
vkslaves/slaves.py
vkslaves/error_handler/__init__.py
vkslaves/error_handler/error_handler.py
vkslaves/errors/__init__.py
vkslaves/errors/errors.py
vkslaves/models/__init__.py
vkslaves/models/models.py
VKSlaves-1.1.1.dist-info/LICENSE
VKSlaves-1.1.1.dist-info/METADATA
VKSlaves-1.1.1.dist-info/WHEEL
VKSlaves-1.1.1.dist-info/top_level.txt
VKSlaves-1.1.1.dist-info/RECORD
