Metadata-Version: 2.1
Name: VKSlaves
Version: 1.1.1
Summary: Asynchronous api wrapper for the game from vk.com called 'slaves'
Home-page: https://github.com/feeeek/vkslaves
Author: FeeeeK (@f_ee_k)
License: gpl-3.0
Keywords: vk-slaves,slaves,vk,vkslaves_bot
Platform: UNKNOWN
Requires-Dist: aiohttp
Requires-Dist: pydantic
Requires-Dist: random-useragent
Requires-Dist: typing-extensions
